[
  {
    "ewe": "atí",
    "phonetic": "/a.tí/",
    "tones": "L-H",
    "pos": "NOUN",
    "french": ["arbre"],
    "morphology": {
      "class": "a-",
      "plural": "atíwo",
      "derivatives": ["atítsu", "atítɔ"]
    },
    "dialects": {
      "anlo": "atí",
      "inland": "atí",
      "gbekplo": "tí"
    },
    "examples": [
      {
        "ewe": "Atí lá le gá.",
        "french": "L'arbre est grand.",
        "gloss": "arbre DÉT être grand"
      }
    ]
  },
  {
    "ewe": "dzo",
    "phonetic": "/dzo/",
    "tones": "H",
    "pos": "VERB",
    "french": ["aller", "marcher"],
    "conjugation": {
      "perfective": "dzo",
      "imperfective": "dzom",
      "future": "ádzo"
    },
    "dialects": {
      "anlo": "dzo",
      "inland": "do",
      "gbekplo": "dzo"
    },
    "examples": [
      {
        "ewe": "Médzo asime.",
        "french": "Je vais au marché.",
        "gloss": "1SG-aller marché"
      }
    ]
  }
]